anastasia/__init__.py
anastasia/airquality.py
anastasia/confighelper.py
anastasia/eat.py
anastasia/joke.py
anastasia/loghelper.py
anastasia/main.py
anastasia/roomcommand.py
anastasia/telegramcalendar.py
anastasia/todolist.py
anastasia/weather.py
anastasia-0.1.0.dist-info/DESCRIPTION.rst
anastasia-0.1.0.dist-info/METADATA
anastasia-0.1.0.dist-info/RECORD
anastasia-0.1.0.dist-info/WHEEL
anastasia-0.1.0.dist-info/entry_points.txt
anastasia-0.1.0.dist-info/metadata.json
anastasia-0.1.0.dist-info/top_level.txt
