Metadata-Version: 2.0
Name: anastasia
Version: 0.1.0
Summary: Telegram bot, student oriented.
Home-page: https://github.com/Anastadev/anastasia/
Author: Anastadev
Author-email: lpw.wisniewski@gmail.com
License: UNKNOWN
Platform: UNKNOWN
Classifier: Programming Language :: Python
Classifier: Natural Language :: French
Classifier: License :: OSI Approved :: GNU General Public License v2 (GPLv2)
Classifier: Programming Language :: Python :: 3.6
Classifier: Topic :: Utilities
Requires-Dist: beautifulsoup4
Requires-Dist: icalendar
Requires-Dist: pymongo
Requires-Dist: python-telegram-bot
Requires-Dist: requests
